colorful/__init__.py
colorful/ansi.py
colorful/colors.py
colorful/core.py
colorful/styles.py
colorful/terminal.py
colorful/utils.py
colorful/data/colornames.json
colorful/data/rgb.txt
colorful-0.5.6.dist-info/LICENSE
colorful-0.5.6.dist-info/METADATA
colorful-0.5.6.dist-info/WHEEL
colorful-0.5.6.dist-info/top_level.txt
colorful-0.5.6.dist-info/RECORD
